pyodide_build/__init__.py
pyodide_build/_f2c_fixes.py
pyodide_build/_py_compile.py
pyodide_build/build_env.py
pyodide_build/common.py
pyodide_build/config.py
pyodide_build/constants.py
pyodide_build/create_package_index.py
pyodide_build/io.py
pyodide_build/logger.py
pyodide_build/pypabuild.py
pyodide_build/pywasmcross.py
pyodide_build/spec.py
pyodide_build/uv_helper.py
pyodide_build/views.py
pyodide_build/xbuildenv.py
pyodide_build/xbuildenv_releases.py
pyodide_build/cli/__init__.py
pyodide_build/cli/build.py
pyodide_build/cli/build_recipes.py
pyodide_build/cli/clean.py
pyodide_build/cli/config.py
pyodide_build/cli/py_compile.py
pyodide_build/cli/skeleton.py
pyodide_build/cli/venv.py
pyodide_build/cli/xbuildenv.py
pyodide_build/out_of_tree/__init__.py
pyodide_build/out_of_tree/app_data.py
pyodide_build/out_of_tree/build.py
pyodide_build/out_of_tree/pypi.py
pyodide_build/out_of_tree/venv.py
pyodide_build/recipe/bash_runner.py
pyodide_build/recipe/builder.py
pyodide_build/recipe/cleanup.py
pyodide_build/recipe/graph_builder.py
pyodide_build/recipe/loader.py
pyodide_build/recipe/skeleton.py
pyodide_build/recipe/spec.py
pyodide_build/recipe/unvendor.py
pyodide_build/tools/emscripten.meson.cross
pyodide_build/tools/cmake/Modules/Platform/Emscripten.cmake
pyodide_build/vendor/_pypabuild.py
pyodide_build/vendor/loky.py
pyodide_build-0.31.1.dist-info/METADATA
pyodide_build-0.31.1.dist-info/WHEEL
pyodide_build-0.31.1.dist-info/entry_points.txt
pyodide_build-0.31.1.dist-info/licenses/LICENSE
pyodide_build-0.31.1.dist-info/RECORD
