Metadata-Version: 2.4
Name: pyodide-build
Version: 0.31.1
Summary: "Tools for building Pyodide"
Project-URL: Homepage, https://github.com/pyodide/pyodide-build
Project-URL: Bug Tracker, https://github.com/pyodide/pyodide-build/issues
Project-URL: Documentation, https://pyodide.org/en/stable/
Author: Pyodide developers
License: MPL-2.0
License-File: LICENSE
Classifier: License :: OSI Approved :: Mozilla Public License 2.0 (MPL 2.0)
Classifier: Operating System :: OS Independent
Classifier: Programming Language :: Python :: 3
Requires-Python: >=3.12
Requires-Dist: auditwheel-emscripten~=0.2.0
Requires-Dist: build~=1.2.0
Requires-Dist: packaging
Requires-Dist: platformdirs
Requires-Dist: pydantic<3,>=2
Requires-Dist: pyodide-cli>=0.3.0
Requires-Dist: pyodide-lock~=0.1.0
Requires-Dist: requests
Requires-Dist: resolvelib
Requires-Dist: rich
Requires-Dist: ruamel-yaml
Requires-Dist: typer>=0.13
Requires-Dist: unearth~=0.6
Requires-Dist: virtualenv
Requires-Dist: wheel
Provides-Extra: test
Requires-Dist: pytest; extra == 'test'
Requires-Dist: pytest-cov; extra == 'test'
Requires-Dist: pytest-httpserver; extra == 'test'
Requires-Dist: types-requests; extra == 'test'
Provides-Extra: uv
Requires-Dist: build[uv]~=1.2.0; extra == 'uv'
